sqs_extended_client/__init__.py
sqs_extended_client/session.py
sqs_extended_client-0.0.10.dist-info/LICENSE
sqs_extended_client-0.0.10.dist-info/METADATA
sqs_extended_client-0.0.10.dist-info/WHEEL
sqs_extended_client-0.0.10.dist-info/top_level.txt
sqs_extended_client-0.0.10.dist-info/RECORD
