Metadata-Version: 2.1
Name: sqs-extended-client
Version: 0.0.10
Summary: AWS SQS extended client functionality from amazon-sqs-java-extended-client-lib
Home-page: https://github.com/QuiNovas/sqs-extended-client
Author: Joseph Wortmann
Author-email: jwortmann@quinovas.com
License: Apache 2.0
Platform: UNKNOWN
Classifier: Development Status :: 4 - Beta
Classifier: Intended Audience :: Developers
Classifier: License :: OSI Approved :: Apache Software License
Classifier: Programming Language :: Python :: 3.7
Requires-Dist: botoinator
